storyscience/__init__.py
storyscience-1.4.6.dist-info/LICENSE
storyscience-1.4.6.dist-info/METADATA
storyscience-1.4.6.dist-info/WHEEL
storyscience-1.4.6.dist-info/top_level.txt
storyscience-1.4.6.dist-info/RECORD
