Metadata-Version: 2.1
Name: storyscience
Version: 1.4.6
Summary: A storyteller
Home-page: https://github.com/23subbhashit/StoryTellar/
Author: subbhashit mukherjee
Author-email: subbhashitmukherjee@gmail.com
License: MIT
Platform: UNKNOWN
Requires-Python: >=3.6
Requires-Dist: numpy (>=1.16.6)
Requires-Dist: pandas (>=1.0.5)
Requires-Dist: seaborn (>=0.10.1)
Requires-Dist: matplotlib (>=3.2.2)
Requires-Dist: plotly (>=4.9.0)
Requires-Dist: scikit-learn (>=0.23.2)
Requires-Dist: tabulate (>=0.8.9)
Requires-Dist: regex (>=2.2.1)
Requires-Dist: nltk (>=3.4.5)
Requires-Dist: tqdm (>=4.45.0)
Requires-Dist: scipy (>=1.4.1)
Requires-Dist: wordcloud (>=1.8.0)
